pydantic_function_models-0.1.9.dist-info/METADATA
pydantic_function_models-0.1.9.dist-info/WHEEL
pydantic_function_models-0.1.9.dist-info/entry_points.txt
pydantic_function_models-0.1.9.dist-info/licenses/LICENSE.txt
pydantic_function_models/__init__.py
pydantic_function_models/log.py
pydantic_function_models/parameters.py
pydantic_function_models/validated_function.py
pydantic_function_models-0.1.9.dist-info/RECORD
